[
    {
      "id": 1, 
      "subject": "Matti pr Sajda", 
      "references": {
        "book": "Sahih Bukhari", 
        "volume": "01", 
        "page": "528", 
        "line": "Hadees# 836"
      }, 
      "description": "Matti pr sajda Nabi (sawaw) krtey thy wo sabit hota hai"
    },
    {
    "id": 2, 
    "subject": "Hazrat Ali | Paoon ka masah", 
    "references": {
        "book": "Sahih Bukhari", 
        "volume": "05", 
        "page": "410", 
        "line": "Hadees# 5616"
    }, 
    "description": "Hazrat Ali k wazu ka zikr hai magar Sar Paoon ki baat adhi bayaan ki.."
    },
    {
        "id": 3, 
        "subject": "Hazrat Ali | Paoon ka masah", 
        "references": {
            "book": "Musnad Ahmed bin Hambal", 
            "volume": "01", 
            "page": "369", 
            "line": "hadees# 737"
        }, 
        "description": "Yaha bayaan howa k Hazrat Ali ne farmaya k Nabi (sawaw) paoon k opper hissey ka masah karte thy, Smartness ye ki urdu tarjumey main Socks/jootey ka word add kardia.. jb k arabi main Paoon tha. --But-- Sunan Abu Dawood main yahi ahadees SOCKS arabic main hain --Musanib abhi shaiba-- main direct paoon pr masah ka mojood hai... mere pass book nhi tu direct check nhi kia"
    },
    {
        "id": 4, 
        "subject": "Hazrat Ali | Kharey ho k pani peena", 
        "references": {
            "book": "Sahih Bukhari", 
            "volume": "05", 
            "page": "409", 
            "line": "hadees# 5615-5616"
        }, 
        "description": "Topic Kharey ho k paani peena - Masjid-e-Koofa main Hazrat Ali ne kharey ho k paani piya aur bataya k kuch loog makroh samajte hain jb k Nabi (sawaw) bhi aise krte thy"
    },
    {
        "id": 5, 
        "subject": "Hazrat Ayesha | Yusuf k gird aurteen | women around Yusuf", 
        "references": {
            "book": "Sahih Muslim", 
            "volume": "01 - English", 
            "page": "531", 
            "line": "hadees# 940"
        }, 
        "description": "End main Bibi ayesha se Allah k Rasool (sawaw) ne farmaya k tum yusuf k gird aurtoon ki tarha ho yaan aziyat dene wali"
    },
    {
        "id": 6, 
        "subject": "Hazrat Fatimah as | Gazabnaak | Jannat", 
        "references": {
            "book": "Sahih Bukhari", 
            "volume": "03", 
            "page": "765", 
            "line": "Hadees# 6767"
        }, 
        "description": "Hazrat Fatima (as) Jannat ki aurtoo ki sardaar hain -  Fatima (as) Mere (sawaw) jism ka tukra hai, jisney usey(as) gazabnaak kia usne muje (sawaw) gazabnaak kia."
    },
    {
        "id": 7, 
        "subject": "Meaning badalna | alaihis salam | Bibi Fatimah as", 
        "references": {
            "book": "Sahih Bukhari", 
            "volume": "05", 
            "page": "737", 
            "line": "Hadees# 6318"
        }, 
        "description": "Yaha arabi main Dadi Fatimah k naam k sath Alaihis-salam hai pr URDU main Raziallah kardia.. jb k Bibi Ayesha k naam k sath kuch nhi"
    },
    {
        "id": 8, 
        "subject": "Ks ki Pervi / Itaba karain? Jo janta hai yaa jo rah nhi janta", 
        "references": {
            "book": "Quran", 
            "volume": "Surah Yunus Chapter 10", 
            "page": "", 
            "line": "Ayat: 35 "
        }, 
        "description": "Jo sahih rah batata hai zyada haqdar hai k uski pervi ki jaye YAA jo khud rah nhi pata - Tm kese faisle karte ho?"
    },
    {
        "id": 9, 
        "subject": "Khalifa - Nabi kisey Khalifa banatey", 
        "references": {
            "book": "Musnad Ahmed bin Hambal", 
            "volume": "11", 
            "page": "99", 
            "line": "Hadees# 24850"
        }, 
        "description": "ayesha said, nabi ney kisi ko b khalifa nhi chuna aur chuntey tu abu bakar aur umar ko"
    },
    {
        "id":10,
        "subject":"Ata'at | Quraish | Muslim",
        "references": {
        "book":"Sahih Muslim",
        "volume":"5",
        "page":"113",
        "line":"Hadees# 4701"
        },
        "description":"Har musalmaan QURAISH k taabey hai"
      },
      {
        "id":11,
        "subject":"Ata'at | Quraish | Muslim",
        "references": {
        "book":"Sahih Muslim",
        "volume":"05",
        "page":"113",
        "line":"Hadees# 4702"
        },
        "description":"Har musalmaan QURAISH k taabey hai"
      },
      {
        "id":12,
        "subject":"Ata'at | Quraish | Muslim",
        "references":{
        "book":"Sahih Muslim",
        "volume":"05",
        "page":"113",
        "line":"Hadees# 4703"
        },
        "description":"Har musalmaan QURAISH k taabey hai"
      },
      {
        "id":13,
        "subject":"Khalifa | Quraish",
        "references": {
        "book":"Sahih Muslim",
        "volume":"05",
        "page":"113",
        "line":"Hadees# 4704"
        },
        "description":"Khilafat hamesha Quraish mai rahegi"
      },
      {
        "id":14,
        "subject":"Ata'at | Quraish | Muslim",
        "references": {
        "book":"mustadrak al sahi",
        "volume":"03",
        "page":"494",
        "line":"Hadees# 5979"
        },
        "description":"Har musalmaan QURAISH k taabey hai"
      },
      {
        "id":15,
        "subject":"Ata'at | Quraish | Muslim",
        "references": {
        "book":"mustadrak al sahi",
        "volume":"03",
        "page":"494",
        "line":"Hadees# 5980"
        },
        "description":"Har musalmaan QURAISH k taabey hai"
      },
      {
        "id":16,
        "subject":"Khalifa | Quraish",
        "references": {
        "book":"mustadrak al sahi",
        "volume":"03",
        "page":"494",
        "line":"Hadees# 5981"
        },
        "description":"khilafat quraish mai rahegi jb k doo loog bhi baqi rahe"
      }
  ]
  